_libxmplite.cp37-win_amd64.pyd
libxmplite.py
libxmplite-1.3.dist-info/LICENSE
libxmplite-1.3.dist-info/METADATA
libxmplite-1.3.dist-info/WHEEL
libxmplite-1.3.dist-info/top_level.txt
libxmplite-1.3.dist-info/RECORD
