Metadata-Version: 2.1
Name: libxmplite
Version: 1.3
Summary: python bindings for the libxmp-lite modplayer library (protracker, screamtracker, ...)
Home-page: https://github.com/irmen/pylibxmplite
Author: Irmen de Jong
Author-email: irmen@razorvine.net
License: MIT
Keywords: sound,audio,playback,tracker,module,protracker,Amiga
Platform: UNKNOWN
Classifier: License :: OSI Approved :: MIT License
Classifier: Development Status :: 4 - Beta
Classifier: Programming Language :: C
Classifier: Programming Language :: Python
Classifier: Programming Language :: Python :: 3.5
Classifier: Programming Language :: Python :: 3.6
Classifier: Programming Language :: Python :: 3.7
Classifier: Programming Language :: Python :: 3.8
Classifier: Topic :: Multimedia :: Sound/Audio
Classifier: Topic :: Multimedia :: Sound/Audio :: Players
Requires-Dist: cffi (>=1.3.0)
